dependency_risk_profiler/__init__.py
dependency_risk_profiler/__main__.py
dependency_risk_profiler/async_http.py
dependency_risk_profiler/config.py
dependency_risk_profiler/models.py
dependency_risk_profiler/analyzers/__init__.py
dependency_risk_profiler/analyzers/base.py
dependency_risk_profiler/analyzers/common.py
dependency_risk_profiler/analyzers/golang.py
dependency_risk_profiler/analyzers/nodejs.py
dependency_risk_profiler/analyzers/python.py
dependency_risk_profiler/cli/__init__.py
dependency_risk_profiler/cli/formatter.py
dependency_risk_profiler/cli/main.py
dependency_risk_profiler/cli/typer_cli.py
dependency_risk_profiler/community/__init__.py
dependency_risk_profiler/community/analyzer.py
dependency_risk_profiler/license/__init__.py
dependency_risk_profiler/license/analyzer.py
dependency_risk_profiler/parsers/__init__.py
dependency_risk_profiler/parsers/base.py
dependency_risk_profiler/parsers/golang.py
dependency_risk_profiler/parsers/nodejs.py
dependency_risk_profiler/parsers/python.py
dependency_risk_profiler/parsers/registry.py
dependency_risk_profiler/parsers/toml.py
dependency_risk_profiler/scorecard/__init__.py
dependency_risk_profiler/scorecard/branch_protection.py
dependency_risk_profiler/scorecard/dependency_update.py
dependency_risk_profiler/scorecard/maintained.py
dependency_risk_profiler/scorecard/security_policy.py
dependency_risk_profiler/scorecard/signed_commits.py
dependency_risk_profiler/scoring/__init__.py
dependency_risk_profiler/scoring/risk_scorer.py
dependency_risk_profiler/secure_release/__init__.py
dependency_risk_profiler/secure_release/code_signing.py
dependency_risk_profiler/secure_release/github_actions_ci_cd.yaml
dependency_risk_profiler/secure_release/release_build.py
dependency_risk_profiler/secure_release/release_management.py
dependency_risk_profiler/supply_chain/__init__.py
dependency_risk_profiler/supply_chain/analyzer.py
dependency_risk_profiler/supply_chain/graph.py
dependency_risk_profiler/supply_chain/trends.py
dependency_risk_profiler-0.3.0.dist-info/METADATA
dependency_risk_profiler-0.3.0.dist-info/WHEEL
dependency_risk_profiler-0.3.0.dist-info/entry_points.txt
dependency_risk_profiler-0.3.0.dist-info/top_level.txt
dependency_risk_profiler-0.3.0.dist-info/RECORD
