Metadata-Version: 2.4
Name: dependency-risk-profiler
Version: 0.3.0
Summary: A tool to evaluate the health and risk of a project's dependencies beyond vulnerability scanning
Home-page: https://github.com/williamzujkowski/dependency-risk-profiler
Author: William Zujkowski
Author-email: William Zujkowski <williamzujkowski@gmail.com>
License: MIT
Project-URL: Homepage, https://github.com/williamzujkowski/dependency-risk-profiler
Project-URL: Issues, https://github.com/williamzujkowski/dependency-risk-profiler/issues
Classifier: Development Status :: 3 - Alpha
Classifier: Intended Audience :: Developers
Classifier: License :: OSI Approved :: MIT License
Classifier: Programming Language :: Python :: 3
Classifier: Programming Language :: Python :: 3.9
Classifier: Programming Language :: Python :: 3.10
Classifier: Programming Language :: Python :: 3.11
Classifier: Programming Language :: Python :: 3.12
Classifier: Topic :: Software Development :: Quality Assurance
Classifier: Topic :: Security
Requires-Python: >=3.9
Requires-Dist: requests>=2.32.2
Requires-Dist: packaging>=23.2
Requires-Dist: colorama>=0.4.6; platform_system == "Windows"
Requires-Dist: pyyaml>=6.0.1
Requires-Dist: matplotlib>=3.7.0
Requires-Dist: networkx>=2.8.8
Requires-Dist: cryptography>=42.0.0
Requires-Dist: urllib3>=2.2.2
Requires-Dist: jinja2>=3.1.5
Requires-Dist: certifi>=2024.7.4
Requires-Dist: werkzeug>=3.0.6
Requires-Dist: tomli>=2.0.1
Requires-Dist: pygments>=2.16.1
Requires-Dist: pillow>=10.2.0
Requires-Dist: typer>=0.9.0
Requires-Dist: rich>=13.5.0
Requires-Dist: aiohttp>=3.8.6
Requires-Dist: httpx>=0.24.1
Requires-Dist: pipdeptree>=2.13.0
Provides-Extra: dev
Requires-Dist: pytest>=7.4.0; extra == "dev"
Requires-Dist: pytest-cov>=4.2.0; extra == "dev"
Requires-Dist: pytest-benchmark>=4.0.0; extra == "dev"
Requires-Dist: pytest-asyncio>=0.21.1; extra == "dev"
Requires-Dist: black>=24.4.0; extra == "dev"
Requires-Dist: isort>=5.13.2; extra == "dev"
Requires-Dist: flake8>=7.0.0; extra == "dev"
Requires-Dist: mypy>=1.9.0; extra == "dev"
Requires-Dist: responses>=0.25.0; extra == "dev"
Requires-Dist: aioresponses>=0.7.4; extra == "dev"
Requires-Dist: tomli>=2.0.1; extra == "dev"
Requires-Dist: tomli-w>=1.0.0; extra == "dev"
Requires-Dist: pre-commit>=3.5.0; extra == "dev"
Provides-Extra: benchmark
Requires-Dist: numpy>=1.24.0; extra == "benchmark"
Provides-Extra: visualization
Requires-Dist: graphviz>=0.20.1; extra == "visualization"
Requires-Dist: python-igraph>=0.10.4; extra == "visualization"
Dynamic: author
Dynamic: home-page
Dynamic: requires-python
